anchorscad_bullet/LICENSE
anchorscad_bullet/__init__.py
anchorscad_bullet/pybullet_viewer.py
anchorscad_bullet/render_bullet.py
anchorscad_bullet-0.1.2.dist-info/METADATA
anchorscad_bullet-0.1.2.dist-info/WHEEL
anchorscad_bullet-0.1.2.dist-info/RECORD
