Metadata-Version: 2.4
Name: anchorscad-bullet
Version: 0.1.2
Summary: AnchorSCAD to PyBullet mesh converter.
Author-email: Gianni Mariani <owebeeone@gmail.com>
Requires-Python: >=3.10
Requires-Dist: anchorscad-core
Requires-Dist: manifold3d
Requires-Dist: numpy
Requires-Dist: pybullet
Requires-Dist: pythonopenscad
Requires-Dist: trimesh
